TracStats-0.6.dist-info/DESCRIPTION.rst
TracStats-0.6.dist-info/METADATA
TracStats-0.6.dist-info/RECORD
TracStats-0.6.dist-info/WHEEL
TracStats-0.6.dist-info/dependency_links.txt
TracStats-0.6.dist-info/entry_points.txt
TracStats-0.6.dist-info/metadata.json
TracStats-0.6.dist-info/top_level.txt
tracstats/__init__.py
tracstats/web_ui.py
tracstats/htdocs/asc.gif
tracstats/htdocs/both.gif
tracstats/htdocs/code.png
tracstats/htdocs/common.css
tracstats/htdocs/desc.gif
tracstats/htdocs/excanvas.compiled.js
tracstats/htdocs/excanvas.js
tracstats/htdocs/jquery-1.6.3.min.js
tracstats/htdocs/jquery.flot.js
tracstats/htdocs/jquery.flot.min.js
tracstats/htdocs/jquery.flot.time.js
tracstats/htdocs/jquery.flot.time.min.js
tracstats/htdocs/jquery.metadata.js
tracstats/htdocs/jquery.sparkline.js
tracstats/htdocs/jquery.sparkline.min.js
tracstats/htdocs/jquery.tablesorter.js
tracstats/htdocs/jquery.tablesorter.min.js
tracstats/htdocs/legend.png
tracstats/htdocs/tickets.png
tracstats/htdocs/wiki.png
tracstats/templates/code.html
tracstats/templates/stats.html
tracstats/templates/tickets.html
tracstats/templates/wiki.html
