Metadata-Version: 2.0
Name: TracStats
Version: 0.6
Summary: A Trac plugin for project statistics
Home-page: http://github.com/trac-hacks/tracstats
Author: John Benediktsson
Author-email: mrjbq7@gmail.com
License: UNKNOWN
Download-URL: http://github.com/trac-hacks/tracstats/zipball/master#egg=TracStats-0.6
Platform: UNKNOWN
Classifier: Development Status :: 4 - Beta
Classifier: Framework :: Trac
Classifier: License :: OSI Approved :: BSD License
